MANIFEST.in
README.md
pyproject.toml
setup.cfg
seafog/__init__.py
seafog/avhrr.py
seafog/detect.py
seafog/gfs.py
seafog/goos_sst.py
seafog/himawari.py
seafog/pgm.py
seafog/utils.py
seafog.egg-info/PKG-INFO
seafog.egg-info/SOURCES.txt
seafog.egg-info/dependency_links.txt
seafog.egg-info/requires.txt
seafog.egg-info/top_level.txt
seafog/res/HMW8.txt
seafog/res/MTS2.txt
seafog/res/__init__.py
seafog/res/landmask.nc
seafog/res/vis_table.txt