Metadata-Version: 2.2
Name: seafog
Version: 1.3.35
Summary: A Python package for marine fog research
Author: Syize
Author-email: Syize <syizeliu@gmail.com>
Requires-Dist: numpy
Requires-Dist: xarray
Requires-Dist: netCDF4
Requires-Dist: pgm-reader
Requires-Dist: rich
Requires-Dist: ephem
Requires-Dist: matplotlib
Requires-Dist: pandas
Requires-Dist: scipy
Requires-Dist: pycurl
Requires-Dist: global-land-mask
Requires-Dist: cartopy
